{"gender": "male", "age": "49 y.o.", "location": "Tijeras, NM 87059, USA", "status": "single", "username": "Tg4372", "ethnicity": "white", "occupation": "Retail", "description": "I am 48 yrs was a single dad of 2 adult children i am loyal honest truthful and respectful been single last 8yrs my son is out of my house so now I looking for a relationship", "match_age": "from 19 to 86", "children": "1-2 living elsewhere", "orientation": "Straight", "religion": "Other", "smoking": "non-smoker", "drinking": "social drinker", "intent": "Friendship, Romance, Serious Relationship, Marriage"}