{"gender": "female", "age": "55 y.o.", "location": "Cdad. de Guatemala, Guatemala", "status": "divorced", "username": "Lorein", "ethnicity": "hispanic", "occupation": "-", "description": "Soy una persona tranquila, respetuosa, soy maestra de ni\u00f1os en el Nivel primaria y me gusta ver documentales en la televisi\u00f3n, me gusta salir por las tardes a caminar o dar unas vueltas en mi bicicleta, me fusta escuchar m\u00fasica, me gusta el caf\u00e9, etc", "match_age": "from 50 to 54", "children": "1-2 living elsewhere", "orientation": "Straight", "religion": "Christian", "smoking": "non-smoker", "drinking": "occasional drinker", "intent": "Friendship"}