{"gender": "male", "age": "54 y.o.", "location": "Provo, UT, USA", "status": "divorced", "username": "ralphlatin", "ethnicity": "hispanic", "occupation": "Sales Representative", "description": "Im a serious man, romantic, lovely, caring, and looking for a serious woman for friendship and after for a relationship to marry", "match_age": "from 36 to 86", "children": "1-2 living elsewhere", "orientation": "Straight", "religion": "Christian", "smoking": "social smoker", "drinking": "social drinker", "intent": "Friendship, Romance, Serious Relationship, Marriage"}