{"gender": "male", "age": "58 y.o.", "location": "San Antonio, TX, USA", "status": "married", "username": "ngreyes", "ethnicity": "hispanic", "occupation": "Retired", "description": "I usually travel and want to make friends before I get there perhaps to share some fun activities such as travel, social outings, get to know the area, etc.", "match_age": "from 30 to 48", "children": "no children", "orientation": "Straight", "religion": "Other", "smoking": "non-smoker", "drinking": "social drinker", "intent": "Fun, Friendship"}