{"gender": "male", "age": "43 y.o.", "location": "Bogot\u00e1, Bogota, Colombia", "status": "divorced", "username": "crisstti", "ethnicity": "hispanic", "occupation": "Technician in electrical maintenance in industrial", "description": "Hello, I am a quiet person, I like reading, swimming, working, studying, knowing natural places, landscapes, eating out, going to the movies. Soon I will enter one of the immigration programs in Canada: Pilot of Rural and Northern Immigration. . . I like music Lorena Mackennit and Enya ... Thank you for reading my profile.\n\r\nNote: it all starts with a friendship", "match_age": "from 29 to 52", "children": "no children", "orientation": "Straight", "religion": "Spiritual", "smoking": "non-smoker", "drinking": "never", "intent": "Friendship"}