{"gender": "male", "age": "44 y.o.", "location": "Campos, Campos dos Goytacazes - State of Rio de Janeiro, Brasil", "status": "divorced", "username": "Edelso", "ethnicity": "white", "occupation": "-", "description": "Soy cubano, enamorado de la vida, cari\u00f1oso, sociable, trabajador y me gusta disfrutar del amor con mi pareja", "match_age": "from 35 to 50", "children": "1-2 living elsewhere", "orientation": "Straight", "religion": "Other", "smoking": "light smoker", "drinking": "occasional drinker", "intent": "Serious Relationship"}