{"gender": "female", "age": "30 y.o.", "location": "Medell\u00edn, Antioquia, Colombia", "status": "single", "username": "Liz123", "ethnicity": "hispanic", "occupation": "Cosm\u00e9ticos", "description": "I am quiet, fun and preserve my ability to astonish, I also love to look after my body and feed; I am a kind woman and I cannot tolerate disrespect\n\r\nSomeone creative, who believes in the magic of new beginnings, I'm more than you can see and I know what I'm worth \n\n\r\nI love to give my best and I also hope to receive it, I am a very loving and romantic woman, but I am also very radical...\u2019don\u2019t be rude whit me ????\u2019\n\r\ni'm not the kind of woman you'll have a hot talk with, don't waste your time ???? \r\n\u26a0\ufe0f i'm not constantly on the app or constantly on the phone, so be patient", "match_age": "from 37 to 86", "children": "want children", "orientation": "Straight", "religion": "Christian", "smoking": "non-smoker", "drinking": "social drinker", "intent": "Romance, Serious Relationship, Marriage"}