{"gender": "male", "age": "27 y.o.", "location": "Oklahoma City, Oklahoma, EE. UU.", "status": "single", "username": "DeAnthoney95", "ethnicity": "black", "occupation": "-", "description": "Estoy soltero buscando por al menos conversaci\u00f3n. Prefiero hablar en espa\u00f1ol pero estoy biling\u00fce", "match_age": "from 19 to 86", "children": "want children", "orientation": "Straight", "religion": "Christian", "smoking": "social smoker", "drinking": "social drinker", "intent": "Fun, Friendship, Romance, Serious Relationship, Marriage"}