{"gender": "male", "age": "58 y.o.", "location": "Gastonia, NC, USA", "status": "single", "username": "Longsnoopy56", "ethnicity": "black", "occupation": "Dietary aide", "description": "I'm honest, faithful, respectful, loyal and down to earth, fun, real gentleman who know how to treat a good woman.", "match_age": "from 30 to 54", "children": "don't want children", "orientation": "Straight", "religion": "Christian", "smoking": "social smoker", "drinking": "occasional drinker", "intent": "Serious Relationship"}