{"gender": "male", "age": "46 y.o.", "location": "Bucaramanga, Santander, Colombia", "status": "divorced", "username": "jhonnydiaz", "ethnicity": "hispanic", "occupation": "enfermero licenciado.. cahumatologo", "description": "aqui un amigo cari\u00f1oso, pana, parcero gentil humilde.... la adversidad solo la buscamos cuando la pereza nos agobia... eso es pecado", "match_age": "from 25 to 50", "children": "1-2 living elsewhere", "orientation": "Straight", "religion": "Christian", "smoking": "non-smoker", "drinking": "social drinker", "intent": "Romance, Serious Relationship"}