{"gender": "male", "age": "50 y.o.", "location": "Everett, WA, USA", "status": "divorced", "username": "Bassclef", "ethnicity": "white", "occupation": "Musician", "description": "I am a writer... a composer of orchestral music .. jazz .. and also a musician... bassist...", "match_age": "from 30 to 58", "children": "no children", "orientation": "Straight", "religion": "Spiritual", "smoking": "non-smoker", "drinking": "occasional drinker", "intent": "Fun, Friendship, Romance, Serious Relationship"}