{"gender": "female", "age": "53 y.o.", "location": "Seattle, WA, USA", "status": "divorced", "username": "Michelle51", "ethnicity": "white", "occupation": "Retired", "description": "My dog TOBY and I are looking for someone UNIQUE. We are respectful honest loyal faithful. Looking for someone who is willing to COMMUNICATE everyday. That's is honest don't play games. Who really truly cares to get to know each other.", "match_age": "from 46 to 58", "children": "don't want children", "orientation": "Straight", "religion": "Christian", "smoking": "light smoker", "drinking": "never", "intent": "Friendship, Serious Relationship"}