{"gender": "female", "age": "32 y.o.", "location": "Bangkok, Thailand", "status": "single", "username": "Kullan", "ethnicity": "asian", "occupation": "salesgirl", "description": "i am simple and caring woman, i am hardworking and i am a salesgirl in shoe store. i grew up in the heart on BKK and learn much about my values and culture. my hobbies are cooking, music, yoga, jogging, taking a long date walk, going to theater with friend, nice conversation, swimming, reading romantic books, spending time with mother and few friends", "match_age": "from 37 to 60", "children": "want children", "orientation": "Straight", "religion": "Atheist", "smoking": "non-smoker", "drinking": "never", "intent": "Friendship, Romance, Serious Relationship, Marriage"}