{"gender": "female", "age": "58 y.o.", "location": "Cape Town, South Africa", "status": "divorced", "username": "MichMAP", "ethnicity": "mixed", "occupation": "Education", "description": "I enjoy socializing with family and friends. I would like to meet someone who is trustworthy. I am interested in an independent, serious-minded Male.", "match_age": "from 50 to 60", "children": "1-2 living with me", "orientation": "Straight", "religion": "Christian", "smoking": "social smoker", "drinking": "social drinker", "intent": "Serious Relationship"}