{"gender": "female", "age": "47 y.o.", "location": "Lima, Per\u00fa", "status": "single", "username": "EstrellaSol", "ethnicity": "hispanic", "occupation": "-", "description": "Sincera, transparente, risue\u00f1a, hogare\u00f1a, me encanta bailar, disfruto de una cena agradable con conversaci\u00f3n interesante con amigos.", "match_age": "from 48 to 60", "children": "no children", "orientation": "Straight", "religion": "Other", "smoking": "non-smoker", "drinking": "occasional drinker", "intent": "Serious Relationship, Marriage"}