{"gender": "male", "age": "63 y.o.", "location": "Westland, MI, USA", "status": "divorced", "username": "RomanticallyYours", "ethnicity": "white", "occupation": "-", "description": "Looking for one woman that wants a very close intimate relationship and is willing to share her thoughts, feelings and desires with me as I shall share mine with her and explore a oneness together \u2764\ufe0f", "match_age": "from 21 to 86", "children": "1-2 living with me", "orientation": "Straight", "religion": "Spiritual", "smoking": "non-smoker", "drinking": "never", "intent": "Fun, Friendship, Romance, Serious Relationship"}