{"gender": "male", "age": "55 y.o.", "location": "Concepci\u00f3n, B\u00edo B\u00edo, Chile", "status": "married", "username": "Subamerica", "ethnicity": "hispanic", "occupation": "-", "description": "Hola , Comencemos por conversar y conocernos . Luego el tiempo lo dir\u00e1 . Soy profesor de filosof\u00eda , se muy poco de Ingles , me gusta leer , hacer deporte , ayudar si se puede , conversar y conocer gente que tenga algo que decir .\n\n\r\nSaludos desde Chile", "match_age": "from 27 to 35", "children": "more than 2 living elsewhere", "orientation": "Straight", "religion": "Christian", "smoking": "non-smoker", "drinking": "social drinker", "intent": "Friendship, Romance, Serious Relationship"}