{"gender": "male", "age": "59 y.o.", "location": "Rundu, Namibia", "status": "divorced", "username": "Veldmens", "ethnicity": "white", "occupation": "Own small business", "description": "I am a very easy guy to be with like to bbq and drink wine or whiskey with my friends go camping and to be in nature", "match_age": "from 36 to 55", "children": "1-2 living elsewhere", "orientation": "Straight", "religion": "Christian", "smoking": "non-smoker", "drinking": "occasional drinker", "intent": "Friendship, Romance, Serious Relationship"}