{"gender": "male", "age": "31 y.o.", "location": "Xalapa-Enr\u00edquez, Ver., M\u00e9xico", "status": "single", "username": "richyvelasco", "ethnicity": "hispanic", "occupation": "-", "description": "Soy muy simp\u00e1tico, divertido y ocurrente, me gusta bailar, viajar y disfrutar.", "match_age": "from 19 to 37", "children": "want children", "orientation": "Straight", "religion": "Christian", "smoking": "light smoker", "drinking": "occasional drinker", "intent": "Fun, Friendship, Romance, Serious Relationship, Marriage"}