{"gender": "male", "age": "45 y.o.", "location": "Montreal, QC, Canada", "status": "divorced", "username": "cozumel", "ethnicity": "hispanic", "occupation": "-", "description": "Caballero con muy buen sentido del humor, te har\u00e9 re\u00edr y hacerte sentir valorada. Busco algo org\u00e1nico. Hombre atl\u00e9tico que le encanta apreciar una buena cena con un buen vino rojo. Me encanta viajar y practicar varios deportes.", "match_age": "from 19 to 86", "children": "1-2 living with me", "orientation": "Straight", "religion": "Christian", "smoking": "non-smoker", "drinking": "social drinker", "intent": "Fun, Friendship, Romance, Serious Relationship"}