{"gender": "male", "age": "47 y.o.", "location": "San Sebasti\u00e1n, Gipuzkoa, Espa\u00f1a", "status": "single", "username": "Frank16", "ethnicity": "white", "occupation": "Director Regional", "description": "Persona sincera, tradicional y cari\u00f1osa. Trabajador y responsable. Sociable, divertido y familiar.", "match_age": "from 32 to 45", "children": "1-2 living with me", "orientation": "Straight", "religion": "Christian", "smoking": "social smoker", "drinking": "social drinker", "intent": "Friendship, Romance, Serious Relationship"}