{"gender": "female", "age": "57 y.o.", "location": "Las Vegas, NV, USA", "status": "single", "username": "Barblv", "ethnicity": "white", "occupation": "Other", "description": "Tired of being lied to and used looking for someone like me cool likes to party some really likes sex and is good at sex", "match_age": "from 45 to 86", "children": "more than 2 living elsewhere", "orientation": "Straight", "religion": "Other", "smoking": "light smoker", "drinking": "occasional drinker", "intent": "Fun, Romance, Serious Relationship"}