{"gender": "male", "age": "32 y.o.", "location": "Provincia de Pastaza, Ecuador", "status": "single", "username": "Brayn", "ethnicity": "mixed", "occupation": "-", "description": "Hoola a todos soy ecuatoriano busco una pareja extranjera para una relacion seria o solo amistad mi personalidad es tranquilo amable honesto disfruto de los paisajes que me rodean y espero encontrar a una princesa para mi.....\r\nSaludos", "match_age": "from 20 to 40", "children": "no children", "orientation": "Straight", "religion": "Christian", "smoking": "non-smoker", "drinking": "occasional drinker", "intent": "Friendship, Serious Relationship, Marriage"}