{"gender": "female", "age": "65 y.o.", "location": "Puebla, Pue., M\u00e9xico", "status": "divorced", "username": "Cupido22", "ethnicity": "hispanic", "occupation": "Real State", "description": "I love dogs so much and I have 6 adorable female dogs. And I\u2019m a real christian lady who loves Jesus over all! Are you the kind of man who could be similar to me to be happy???", "match_age": "from 19 to 86", "children": "no children", "orientation": "Straight", "religion": "Christian", "smoking": "non-smoker", "drinking": "occasional drinker", "intent": "Marriage"}