{"gender": "male", "age": "22 y.o.", "location": "Hope Mills, Carolina del Norte, EE. UU.", "status": "single", "username": "Jhamir", "ethnicity": "hispanic", "occupation": "Constructor", "description": "Me gusta la musica tengo 3 semanas aqui no conozco a nadie", "match_age": "from 19 to 86", "children": "no children", "orientation": "Straight", "religion": "Spiritual", "smoking": "social smoker", "drinking": "social drinker", "intent": "Fun, Friendship, Romance, Serious Relationship, Marriage"}