{"gender": "male", "age": "42 y.o.", "location": "Olon, Ecuador", "status": "widowed", "username": "Xanderbeach", "ethnicity": "white", "occupation": "propietario", "description": "Soy un gringuito en la playa esperando la que quiere compartir conmigo este belleza de la vida.", "match_age": "from 24 to 40", "children": "1-2 living elsewhere", "orientation": "Straight", "religion": "Spiritual", "smoking": "non-smoker", "drinking": "social drinker", "intent": "Romance, Serious Relationship, Marriage"}