{"gender": "male", "age": "49 y.o.", "location": "Medell\u00edn, Antioquia, Colombia", "status": "divorced", "username": "Albeiromar", "ethnicity": "black", "occupation": "Administrador de empresas", "description": "Soy profesional, educado, sincero y alegre. Me gusta el deporte, trabajar y a la vez disfrutar viajando y conociendo nuevos paisajes.", "match_age": "from 35 to 55", "children": "1-2 living elsewhere", "orientation": "Straight", "religion": "Christian", "smoking": "non-smoker", "drinking": "social drinker", "intent": "Serious Relationship"}