{"year_reported": "2015", "month_reported": "10", "username": " sweetlara69", "name": " Lara", "age": " 32", "occupation": " Design Analyst", "status": " single", "inet": " 203.56.188.119", "description": "\nAs you can probably tell, I am an optimist and also a romantic at heart. I enjoy doing little things for my partner to show them I care. I am not materialistic or high maintenance.", "email": " philmur169@gmail.com", "tags": ["Female profiles", "love scammer"], "gender": "female", "images": ["sweetlara691.jpg"]}