{"year_reported": "2015", "month_reported": "02", "username": " dorcasj", "name": " Dorcas or Yolanda", "age": " 29 or 33", "occupation": " Art & Design", "status": " single", "inet": " 82.145.209.171", "description": "\nI am reliable, feminine, well-balanced and very easy-going lady wishing to have her own happy and harmonious family. My mood is usually very high, and I am very positive and cheerful, many-sided and optimistic, gentle and patient. I am well-educated and intelligent. I also enjoy to make pleasant things to those I love.", "email": " dorcasj5102@gmail.com", "tags": ["Female profiles", "badoo", "love scammer"], "gender": "female", "images": ["dorcasj1.jpg"]}