{"year_reported": "2017", "month_reported": "06", "username": " AbottDavid", "name": " David Abott", "age": " 57", "occupation": " manager", "status": " divorced", "inet": " 41.144.164.193", "description": "\nI work as a Manager in an Independent men that deals on cable wires for telecommunication and also for industrial building. I believe a man can never rate him self to be good, but rated by people around him. So i consider my self to be rated by the people around me.", "email": " bobbyabott@gmail.com", "tags": ["Male profiles", "metrodate"], "gender": "male", "images": ["AbottDavid1.jpg", "AbottDavid2.jpg", "AbottDavid3.jpg", "AbottDavid4.jpg"]}