{"year_reported": "2015", "month_reported": "03", "username": " KseniyaV", "name": " Kseniya", "age": " 32", "occupation": " Economist", "status": " single", "inet": " 78.213.228.230", "description": "\nHi! I\u2019m an ordinary girl from Russia. I would like to meet for a serious relationship with a kind, caring and decent man. Please note that I\u2019m interested in dating is only for a serious relationship and for a date in the future. Those interested in the game, or some entertainment, please pass my application. Even the most evil person has a smile on his face when he is told that he is loved. Perhaps this is the real happiness \u2026 v.kseniya2014 (at) yandex (dot) ru", "email": " v.kseniya2014@yandex.ru", "tags": ["Female profiles", "dating-europe", "russian scammer", "site4dating"], "gender": "female", "images": ["KseniyaV1.jpg"]}