{"year_reported": "2018", "month_reported": "11", "username": " azayon", "name": " Reid Rushing", "age": " 49", "occupation": " media", "status": " single", "inet": " 24.241.210.105", "description": "\nI am very loving and outgoing, though can also be reserved. I am independent, yet dedicated in my relationships with others. Honesty is very important to me. I value getting to know someone for who they are, and then want to grow with them. I am genuine \u2013 so what you see is what you get!! Laughing is what I do best, and try to make the most out of life. Travel is a fun part of life and I enjoy taking road trips and cruising the seas. Spending quality time with family and friends and is important to me! I\u2019m a kid at heart and love being around children.", "email": " azayon007@gmail.com", "tags": ["Male profiles", "love scammer"], "gender": "male", "images": ["azayon1.jpg", "azayon2.jpg", "azayon3.jpg", "azayon4.jpg", "azayon5.jpg", "azayon6.jpg"]}