{"year_reported": "2017", "month_reported": "10", "username": " lawredanielle", "name": " Lawre Danielle", "age": " 38", "occupation": " fashion", "status": " single", "phone": " 469-844-8702", "inet": " 50.244.85.17", "description": "\nI\u2019m an extremely simple person with a lot to give out\u2026 I\u2019m fit, intelligent, sensitive, heath conscious woman seeking someone who has it all. I\u2019m at a great point in life and am somewhat of a kind at heart.. i am educated, hardworking, achievement oriented and fun-loving one if we could be friends? you can drop a mail or text me at (four six nine eight four four eight seven zerio two/ lawredanielle at gmail dot com) if you are interested. I\u2019ve been successful in the pursuit and i love what I do, it\u2019s a passion for me! I smile a lot because it is what i am recongnized for", "email": " lawredanielle@gmail.com", "tags": ["Female profiles", "hangouts", "love scammer"], "gender": "female", "images": ["lawredanielle1.jpg", "lawredanielle2.jpg"]}