{"year_reported": "2015", "month_reported": "11", "username": " anthony789", "name": " Anthony Andrew", "age": " 52", "occupation": " business", "status": " widowed", "inet": " 116.202.38.146", "description": "\nI am Anthony very good looking young man,well educated and working with one of reputed company. I like traveling,music watching football.Am here looking for loving,caring,faithful girl for marriage not long time relationship.I am successful person when it comes to my work by god\u2019s grace i am blessed with a daughter and i have everything i need.all i need is that special one in my life with whom i can see the rising sun a", "email": " anthonydandrew@hotmail.com", "tags": ["Male profiles", "romance scammer"], "gender": "male", "images": ["anthony7891.jpg"]}