{"year_reported": "2015", "month_reported": "12", "username": " damon11", "name": " Muloshi Damon", "age": " 30", "occupation": " teacher", "status": " single", "inet": " 186.71.22.10", "description": "\nI\u2019m looking for an open, kind, serious, confident, cheerful, responsible man, who is ready to take me for who i am, I hope to create a happy, secure relationship with a nice man, I would love to have a loving and happy home in a nice house where everyone feels good to come home to, I think a man must take care of his woman and (family) first,I have a dream to meet the person with whom it is possible to live my life with.", "email": " muloshidamon11@gmail.com", "tags": ["Female profiles", "love scammer"], "gender": "female", "images": ["damon111.jpg"]}