{"year_reported": "2013", "month_reported": "07", "username": " awhy101", "name": " James Daniel", "age": " 50", "occupation": " \u2013", "status": " widower", "inet": " \u2013", "description": "\nI describe myself as Articulate and Attractive. I am kind, fun and loyal. I have positive outlook on life and I have visions of great success and for me, failure is not an option. I enjoy traveling, fine dining as well as cooking at home. My favorite tv show is Dr.\u201dHouse\u201d. What sets me apart from the rest is my charming and enthusiastic personality ;).I especially enjoy the company of a highly intelligent lady. I appreciate a woman that is honest and believes in mentoring and is willing to give critique as well as corrective criticism. My ideal match would enjoy travelling, her work, fine dining and cooking. Meaningful conversation over dinner is important. Wouldn\u2019t you agree?", "email": " jdaniel231@yahoo.com", "tags": ["Male profiles", "confirio", "love scammer"], "gender": "male", "images": ["awhy1011.jpg"]}