{"year_reported": "2018", "month_reported": "09", "username": " Mm097", "name": " Bob Marshall", "age": " 40", "occupation": " Administrative", "status": " single", "inet": " 27.122.12.243 or\u00a027.122.12.239", "description": "\nHi, my name is Max. I live in Texas , USA now and I just signed onto this site to find that dream match. I am easy going , calm and I like the nature and animals . I am also very romantic and I hope I get attracted to someone I would love and be the king of her world .", "email": " bobmarshall097@gmail.com", "tags": ["Male profiles", "hangouts", "romance scammer"], "gender": "male", "images": ["Mm0971.jpg", "Mm0972.jpg"]}