{"year_reported": "2018", "month_reported": "10", "username": " Prieto", "name": " Gabriel Prieto Villalba", "age": " 55", "occupation": " engineering", "status": " single", "inet": " 49.200.137.66", "description": "\nI need a life partner whom we can to spend the rest of our life together someone who is friendly, honest, caring, trustworthy and God fearing i find very much peace and tranquility here i`m 5`11\u2033 190 bls with a athletic build, mentally stable, physically fit a good listener God fearing, and a positive person.I am real easy person to talk to and a loving and outgoing father.", "email": " gabrielprietovillalba@gmail.com", "tags": ["Male profiles", "Aaron Ramos", "romance scammer"], "gender": "male", "images": ["Prieto1.jpg"]}