{"year_reported": "2018", "month_reported": "03", "username": " Paola103", "name": " Paola Crane", "age": " 37", "occupation": " nurse", "status": " divorced", "inet": " 99.101.87.241", "description": "\nI am looking for a man who is honest, faithful, loyal, sincere, caring and loving man who is willing to give me his love and heart. Well I\u2019m a loving, caring, honest woman with average smarts, although not into Games. I have morals, looking for a man who is the same\u2026 A man of his words. I can be independent, but looking to find someone I can rely on.", "email": " paolacrane@gmail.com", "tags": ["Female profiles"], "gender": "female", "images": ["Paola1031.jpg"]}