{"year_reported": "2016", "month_reported": "06", "username": " debbie09", "name": " Debbie Cole", "age": " 30", "occupation": " student", "status": " single", "inet": " 197.210.173.23", "description": "\nI\u2019m a woman who is very simple in heart. To put it mildy, I just enjoy great company. Love to hold hands as we walk along the beach. Sharing the view from a snow covered mountain cabin at sunset.", "email": " yemmit09@gmail.com", "tags": ["Female profiles", "facebook"], "gender": "female", "images": ["debbie091.jpg"]}