{"year_reported": "2016", "month_reported": "09", "username": " Jimmy32", "name": " James White", "age": " 56", "occupation": " self employed", "status": " divorced", "inet": " 46.101.109.194", "description": "\nSingle dad with one Daughter ,am 5\u20198 ,brown eyes, dark brown hair, Caucasian(white), i have a Clever Quick Witted sense of humor, i don\u2019t smoke, don\u2019t drink, christian, I like Dining, Outdoor Activities, Reading, Watching Sports, Computers-Internet, Playing Sports.I am a nice man seeking for a caring and honest woman to spend the rest of my life with. I am looking for a woman in his 50_55 for long time companionship.So if interesting. Look me up", "email": " jwhite19u@gmail.com", "tags": ["Male profiles", "facebook", "love scammer"], "gender": "male", "images": ["Jimmy321.jpg", "Jimmy322.jpg", "Jimmy323.jpg"]}