{"year_reported": "2017", "month_reported": "03", "username": " harrisonmorganaussie", "name": " Harrison Mike Morgan", "age": " 47", "occupation": " Administration", "status": " divorced", "inet": " 80.62.127.143", "email": " harrisonmorganaussie@gmail.com", "tags": ["Male profiles", "facebook", "metrodate", "romance scammer", "tagged"], "gender": "male", "images": ["harrisonmorganaussie1.jpg", "harrisonmorganaussie2.jpg", "harrisonmorganaussie3.jpg", "harrisonmorganaussie4.jpg", "harrisonmorganaussie5.jpg", "harrisonmorganaussie6.jpg", "harrisonmorganaussie7.jpg", "harrisonmorganaussie8.jpg", "harrisonmorganaussie9.jpg"]}