{"year_reported": "2016", "month_reported": "12", "username": " maryyb", "name": " Marry Betty", "age": " 35", "occupation": " shopkeeper", "status": " single", "inet": " 172.98.84.179", "description": "\nI am a very caring person and down to earth. I like to fish, bowl, go out for dinner and a movie or stay in and cudlle and watch a movie, go out for drinks and dance.Ihave been divoriced for a year. I am not a materialistic person hangout on g m a i l at marrybety27", "email": " marrybetty27@gmail.com", "tags": ["Female profiles", "hangouts", "love scammer", "pof"], "gender": "female", "images": ["maryyb1.jpg", "maryyb2.jpg"]}