{"year_reported": "2016", "month_reported": "07", "username": " Celsonb", "name": " Belford Celso", "age": " 50", "occupation": " military", "status": " divorced", "inet": " 162.216.17.62", "description": "\nI\u2019m Originally from Italy and by nationality i became a citizen of the greatest country in the world US of A. I am hard working and I like my job because through my job i have been able to protect those who can not protect themselves against the wicked people of this world.Some of my hobbies are cooking, Singing and playing cards\u2026but not for gambling ..lol", "email": " belford000008@gmail.com", "tags": ["Male profiles", "connectingsingles", "facebook", "military scammer"], "gender": "male", "images": ["Celsonb1.jpg", "Celsonb2.jpg", "Celsonb3.jpg", "Celsonb4.jpg", "Celsonb5.jpg", "Celsonb6.jpg", "Celsonb7.jpg", "Celsonb8.jpg", "Celsonb9.jpg"]}