{"year_reported": "2015", "month_reported": "03", "username": " carnel", "name": " Carnel James", "age": " 49", "occupation": " military", "status": " single", "inet": " 216.82.254.111", "description": "\nam a responsible love and man caring man looking for a serious date a love and caring woman scammer please stay away from me you can see am a millitary man i want a woman that we take good care of my daughter you can also add me on carnel.james@yahoo.com", "email": " carnel.james@yahoo.com", "tags": ["Male profiles", "confirio", "military scammer"], "gender": "male", "images": ["carnel1.jpg"]}