{"year_reported": "2016", "month_reported": "07", "username": " kevin", "name": " Kevin Knight", "age": " 54", "occupation": " engineer", "status": " divorced", "inet": " 176.126.69.189", "description": "\nI am easy going loving and caring and soft spoken, easy to understand and happy to be friend with. I have always wanted the love of my life to be understanding, loving, caring, and faithful. I want someone who would accept me for who I am.", "email": " knight_kevin@outlook.com", "tags": ["Male profiles", "metrodate", "romance scammer"], "gender": "male", "images": ["kevin1.jpg", "kevin2.jpg"]}