{"year_reported": "2012", "month_reported": "07", "username": " phinar", "name": " Phina Edgar", "age": " 23", "occupation": " nursing", "status": " divorced", "inet": " 46.166.159.57", "description": "\nMy name is Phina Edgar.I am girl i need a serious and God fearing person for serious relationship; Im black in complexion,6.7ft tall with long hair and single. I have got my unique nature that makes me what I am today and to the level that operate today.You can contact me so that i can send you my pictures and more details about myself.", "email": " phinaedgar@aol.com", "tags": ["Female profiles", "romance scammer", "waydate"], "gender": "female", "images": ["phinar1.jpg"]}