{"year_reported": "2016", "month_reported": "10", "username": " fatash2080", "name": " Natalia Gomez", "age": " 28", "occupation": " student", "status": " single", "inet": " 41.218.220.77", "description": "\nI\u2019m a happy, healthy, adventurous woman with a real zest for life. I am a fiercely loyal friend and lover and expect the same in return. I\u2019m known to have a quick wit and a sharp sense of humor\u2026am a good joke-teller, but I have a funny take on life\u2019s situations. You certainly don\u2019t have to be a perfect special woman to earn a place alongside me BUT it would be appealing to me if you were confident, masculine and sexy!", "email": " nataliagomez88@yahoo.com", "tags": ["Female profiles", "Briana Lee", "love scammer"], "gender": "female", "images": ["fatash20801.jpg", "fatash20802.jpg"]}