{"year_reported": "2013", "month_reported": "05", "username": " Alfred", "name": " Alfred Scott", "age": " 56", "occupation": " engineer", "status": " single", "inet": " 175.144.205.67", "description": "\nI am outgoing with a great sense of humor. I am very affectionate who still believes in chivalry. I love music ranging from the blues, rock and classical. I also enjoy reading a wide variety of books. I am looking for someone who has similar taste, but can introduce me to new things. Laughing, being affectionate and easy going would be great with me. I am looking forward to a new chapter in my life.", "email": " alfredscott879@yahoo.com", "tags": ["Male profiles", "confirio"], "gender": "male", "images": ["Alfred1.jpg", "Alfred2.jpg"]}