{"year_reported": "2016", "month_reported": "08", "username": " Annualman", "name": " David", "age": " 66 or 68", "occupation": " Engineers", "status": " widowed", "inet": " 77.234.44.182", "description": "\nI am Italian but lived in Greece before moving to the United States.\nI love to have fun when I am around people and when I am home I am pretty much Mr. Chill. God knows my wants and needs because He knows everything. I want someone to spend my life with someone to share a life with. Someone who loves me for me. Even my weird nerdy like tendencies, My moodiness at times cause yea I\u2019m a Pisces, a best friend, a soulmate. Someone to sings songs with because sometimes a song come on and you just want to sing it, I don\u2019t like to focus on the negative. I offer you my heart and soul to that one person who wants it and shows me they need it. Wait only God can have our souls. : ) If i am lucky enough to have your heart I will cherish it forever. I am down to earth, I am loving and caring, honest and loyal, Passionate and affectionate. I am waiting to share my life with someone in a mutual loving and understanding till death do us part relationship", "email": " Mdavid6060@gmail.com", "tags": ["Male profiles", "pof", "romance scammer"], "gender": "male", "images": ["Annualman1.jpg"]}