{"year_reported": "2015", "month_reported": "06", "username": " heartopen00", "name": " Elizabeth Gilmore", "age": " 36", "occupation": " registered nurse", "status": " single", "inet": " 109.127.8.245", "description": "\nam a simple and gentle, responsible and intelligent, affectionate and optimistic, conservative and positive, down to earth and an easy going person (to mention but a few). I work as a researcher micro / Microbiologist, never a lazy type and to not really like to depend on others. I have some degree of humor, love to laugh, and would do anything interesting for fun. I like listening to music , watch TV (movies of different kind mostly documentary, comedy, action, adventure, sci-fi horror but never \u2026\u2026 I like watching some sports also", "email": " gilmoree41@yahoo.com.au", "tags": ["Female profiles", "facebook", "love scammer"], "gender": "female", "images": ["heartopen001.jpg", "heartopen002.jpg"]}