{"year_reported": "2016", "month_reported": "10", "username": " kelvinsteven", "name": " Steve Kelvin", "age": " 49", "occupation": " army", "status": " widowed", "inet": " 197.211.63.12", "description": "\nI am SGT kelvin,i am a widower, i lost my wife in an automobile accident, i am here for a serious relationship,i and my kid have really missed the comfort and care of a wife, i have been in short relationships for the past few years but it didn\u2019t get serious..", "email": " jboscolifa@yahoo.com", "tags": ["Male profiles", "military scammer"], "gender": "male", "images": ["kelvinsteven1.jpg", "kelvinsteven2.jpg", "kelvinsteven3.jpg"]}