{"year_reported": "2016", "month_reported": "02", "username": " Wendy001", "name": " Wendy Smitth", "age": " 35", "occupation": " nurse", "status": " single", "inet": " 217.64.42.179", "description": "\nopen-minded, god fearing.. loyal, faithfulness , trust worthy, hard working open minded love and caring open-minded, god fearing.. loyal, faithfulness , trust worthy, hard working open minded love and caring open-minded, god fearing.. loyal, faithfulness , trust worthy, hard working open minded love and caring open-minded, god fearing.. loyal, faithfulness , trust worthy, hard working open minded love and caring", "tags": ["Female profiles", "confirio", "facebook", "flirtbox", "topface"], "gender": "female", "images": ["Wendy0011.jpg", "Wendy0012.jpg"]}