{"year_reported": "2016", "month_reported": "10", "username": " franc", "name": " Chris Jason", "age": " 46", "occupation": " Investment Broker", "status": " divorced", "inet": " 97.107.129.8", "description": "\nmy name is chris jason and am working as an accountant in a firm,am new in this and am hoping to make new friends but what am realy looking for is a caring,loving,and responsible woman to start a serious relationship with.i went through your profile and i like it .you can add me up on frandams2000@gmail.com or set up a yahoo messenger.if you dont have one after the process you can add me to your yahoo list email and inform me and I will open one so we can talk and get to known each other better.i will be expecting you. thank you", "email": " frandams2000@gmail.com", "tags": ["Male profiles"], "gender": "male", "images": ["franc1.jpg"]}