{"year_reported": "2017", "month_reported": "04", "username": " jennefer", "name": " Jennefer Nelson", "age": " 32", "occupation": " self employed", "status": " single", "inet": " 207.244.86.226", "description": "\ni will like to introduce little about myself.\nmy name is jennefer and i am an american by birth,but i presently live and work here in frank furt,am a very simple person with a lot of love and i love the sense of humor i am single with no kid.", "email": " jennefernelson2000@gmail.com", "tags": ["Female profiles", "hangouts"], "gender": "female", "images": ["jennefer1.jpg"]}